lyrics_displayer/__init__.py
lyrics_displayer/utils.py
lyrics_displayer/players/__init__.py
lyrics_displayer/players/main.py
lyrics_displayer/players/sonos.py
lyrics_displayer-0.7.8.data/scripts/sing-along
lyrics_displayer-0.7.8.dist-info/METADATA
lyrics_displayer-0.7.8.dist-info/RECORD
lyrics_displayer-0.7.8.dist-info/WHEEL
lyrics_displayer-0.7.8.dist-info/top_level.txt
