Metadata-Version: 2.1
Name: lyrics-displayer
Version: 0.7.8
Summary: Displays lyrics of songs played on Sonos system.
Home-page: http://github.com/alpha1d3d/lyrics-displayer
Author: Jonathan Loo
Author-email: alpha1d3d@hotmail.com
License: MIT
Keywords: sonos lyrics lyricfetch
Platform: UNKNOWN
Classifier: Development Status :: 3 - Alpha
Classifier: License :: OSI Approved :: MIT License
Classifier: Programming Language :: Python :: 3.6
Requires-Python: >=3.6
Requires-Dist: soco
Requires-Dist: lyricfetch
Requires-Dist: python-magic-bin
